etoolkit/__init__.py
etoolkit/__main__.py
etoolkit/etoolkit.py
etoolkit-2.1.0.dist-info/COPYING
etoolkit-2.1.0.dist-info/LICENSE
etoolkit-2.1.0.dist-info/METADATA
etoolkit-2.1.0.dist-info/WHEEL
etoolkit-2.1.0.dist-info/entry_points.txt
etoolkit-2.1.0.dist-info/top_level.txt
etoolkit-2.1.0.dist-info/RECORD
