Metadata-Version: 2.1
Name: etoolkit
Version: 2.1.0
Summary: A simple toolkit for setting environment variables in a flexible way
Home-page: https://github.com/blackm0re/etoolkit
Author: attr: etoolkit.__author__
Author-email: sgs@pichove.org
Project-URL: Bug Tracker, https://github.com/blackm0re/etoolkit/issues
Project-URL: Source, https://github.com/blackm0re/etoolkit
Classifier: Development Status :: 5 - Production/Stable
Classifier: Environment :: Console
Classifier: Intended Audience :: Developers
Classifier: Intended Audience :: System Administrators
Classifier: License :: OSI Approved :: GNU General Public License v3 or later (GPLv3+)
Classifier: Programming Language :: Python :: 3
Classifier: Programming Language :: Python :: 3.9
Classifier: Programming Language :: Python :: 3.10
Classifier: Programming Language :: Python :: 3.11
Classifier: Programming Language :: Python :: 3.12
Classifier: Programming Language :: Python :: 3.13
Classifier: Programming Language :: Python :: 3.14
Classifier: Operating System :: POSIX
Classifier: Topic :: Security :: Cryptography
Requires-Python: >=3.9
License-File: LICENSE
License-File: COPYING
Requires-Dist: cryptography>=3.2
